iprovide/__init__.py
iprovide/exceptions.py
iprovide/interface.py
iprovide-0.1.1.dist-info/LICENSE
iprovide-0.1.1.dist-info/WHEEL
iprovide-0.1.1.dist-info/METADATA
iprovide-0.1.1.dist-info/RECORD
