Metadata-Version: 2.1
Name: iprovide
Version: 0.1.1
Summary: Provides a simple but effective  interface definition library.
Author: David James McCorrie
Author-email: djmccorrie@gmail.com
Requires-Python: >=3.6,<4.0
Classifier: Programming Language :: Python :: 3
Classifier: Programming Language :: Python :: 3.6
Classifier: Programming Language :: Python :: 3.7
Classifier: Programming Language :: Python :: 3.8
